GenchAPI/__init__.py
GenchAPI/sign.py
GenchAPI-0.0.1.dist-info/LICENSE
GenchAPI-0.0.1.dist-info/METADATA
GenchAPI-0.0.1.dist-info/WHEEL
GenchAPI-0.0.1.dist-info/top_level.txt
GenchAPI-0.0.1.dist-info/RECORD
